Workbook

Sheet Contratacoes 2026
A1: # | B1: Processo / Modalidade | C1: Fundamento legal | D1: Objeto | E1: Fornecedor | F1: Valor (R$) | G1: Situacao | H1: CNAE (subclasse) | I1: Descricao CNAE | J1: Conta p/ limite art.75 I/II? | K1: Exercicio | L1: Fonte / Observacao
A2: 1 | B2: Dispensa 001/2026 (presumida) | C2: Art. 75, II (presumido) | D2: Aquisicao de certificados digitais (e-CPF e e-CNPJ, modelo A1, ICP-Brasil) | E2: Imperio Certificado Digital LTDA (menor preco: R$ 79,00/certificado) | F2: 158 | G2: Propostas recebidas - SEM ratificacao/homologacao nos autos (nao e possivel afirmar concluido) | H2: 63.19-4/00 | I2: Portais, provedores de conteudo e outros servicos de informacao na internet (subclasse que abrange registro/cadastramento de usuarios para certificacao digital) | J2: A confirmar (depende de ratificacao) | K2: 2026 | L2: PROPOSTAS/IMPERIO CERTIFICADOS - e-CPF R$79,00 + e-CNPJ R$79,00 = R$158,00. Proposta concorrente (Confianca) ofertou R$200,00.
A3: 2 | B3: Processo 002/2026 - Dispensa 002/2026 | C3: Art. 75, II | D3: Locacao de veiculos por diaria (sedan) | E3: SL Veiculos | F3: 18200 | G3: Concluido (ratificado) | H3: 77.11-0/00 | I3: Locacao de automoveis sem condutor | J3: Sim | K3: 2026 | L3: REGISTRO_CONTRATACOES_2026.md #2; ratificado 22/01/2026
A4: 3 | B4: Processo 003/2026 - Inexigibilidade 001/2026 | C4: Art. 74 (inexigibilidade) | D4: Auditoria contabil/financeira das demonstracoes da ASPPI (2021-2025) | E4: Nottoria Consultoria e Auditoria LTDA | F4: 25000 | G4: Concluido (contrato assinado) | H4: 69.20-6/02 | I4: Atividades de consultoria e auditoria contabil e tributaria | J4: Nao (inexigibilidade) | K4: 2026 | L4: REGISTRO_CONTRATACOES_2026.md #3; 09/02/2026
A5: 4 | B5: Processo 006/2026 - Dispensa 004/2026 | C5: Art. 75, II | D5: Fornecimento parcelado de generos alimenticios, higiene, limpeza, descartaveis, agua mineral e GLP | E5: Mercearia Ita Minas + Supermercado Boa Esperanca | F5: 21892.75 | G5: Concluido (valor global multifornecedor a confirmar) | H5: 47.11-3/02 | I5: Comercio varejista de mercadorias em geral, predominancia alimenticia (supermercados) - confirmar porte/enquadramento exato de cada fornecedor | J5: Sim | K5: 2026 | L5: REGISTRO_CONTRATACOES_2026.md #4; valor exibido e so da Mercearia Ita Minas
A6: 5 | B6: Processo 005/2026 - Dispensa 003/2026 | C6: Art. 75, II | D6: Aquisicao de materiais de expediente (capas de processo) | E6: Embacom | F6: 5750 | G6: Concluido | H6: 47.61-0/03 | I6: Comercio varejista de artigos de papelaria | J6: Sim | K6: 2026 | L6: REGISTRO_CONTRATACOES_2026.md #5; 02/03/2026
A7: 6 | B7: Processo 004/2026 - Inexigibilidade 002/2026 | C7: Art. 74 (inexigibilidade) | D7: 4 inscricoes - 660 Curso de Capacitacao (BH) | E7: Instituto Global de Administracao Publica | F7: 5560 | G7: Concluido | H7: 85.99-6/04 | I7: Treinamento em desenvolvimento profissional e gerencial | J7: Nao (inexigibilidade) | K7: 2026 | L7: REGISTRO_CONTRATACOES_2026.md #6; 11/02/2026
A8: 7 | B8: Processo 015/2026 - Dispensa 008/2026 | C8: Art. 75, II | D8: Aquisicao de materiais de expediente (papelaria) | E8: Agostinho Ribeiro (Bazar Central) | F8: 8603.8 | G8: Concluido (homologado) | H8: 47.61-0/03 | I8: Comercio varejista de artigos de papelaria | J8: Sim | K8: 2026 | L8: Termo de Adjudicacao e Homologacao anexado pelo usuario - Proc. 015/2026, Dispensa 008/2026, homologado em 17/04/2026. Total do fornecedor: R$ 8.603,80 (17 itens de papelaria).
A9: 8 | B9: Processo 007/2026 - Inexigibilidade 003/2026 | C9: Art. 74 (inexigibilidade) | D9: 2 inscricoes - 663 Curso de Capacitacao (BH) | E9: Instituto Global de Administracao Publica | F9: 2780 | G9: Concluido | H9: 85.99-6/04 | I9: Treinamento em desenvolvimento profissional e gerencial | J9: Nao (inexigibilidade) | K9: 2026 | L9: REGISTRO_CONTRATACOES_2026.md #8; 02/03/2026
A10: 9 | B10: Processo 008/2026 - Inexigibilidade 004/2026 | C10: Art. 74 (inexigibilidade) | D10: 4 inscricoes - 665 Curso de Capacitacao (BH) | E10: Instituto Global de Administracao Publica | F10: 5560 | G10: Concluido | H10: 85.99-6/04 | I10: Treinamento em desenvolvimento profissional e gerencial | J10: Nao (inexigibilidade) | K10: 2026 | L10: REGISTRO_CONTRATACOES_2026.md #9; 16/03/2026
A11: 10 | B11: Processo 012/2026 - Inexigibilidade 006/2026 | C11: Art. 74 (inexigibilidade) | D11: Licenciamento de software p/ coleta de dados e integracao a emissao da CIN | E11: Valid S.A | F11: 2500 | G11: Concluido | H11: 62.03-1/00 | I11: Desenvolvimento e licenciamento de programas de computador nao-customizaveis | J11: Nao (inexigibilidade) | K11: 2026 | L11: REGISTRO_CONTRATACOES_2026.md #10; 01/04/2026
A12: 11 | B12: Processo 009/2026 - Inexigibilidade 005/2026 | C12: Art. 74 (inexigibilidade) | D12: 2 inscricoes - curso Parlamento Jovem, Camara Mirim e Educacao Civica | E12: CEAP - Treinamento Profissional e Gerencial LTDA | F12: 3980 | G12: Concluido | H12: 85.99-6/04 | I12: Treinamento em desenvolvimento profissional e gerencial | J12: Nao (inexigibilidade) | K12: 2026 | L12: REGISTRO_CONTRATACOES_2026.md #11; 16/03/2026
A13: 12 | B13: Processo 010/2026 - Dispensa 005/2026 | C13: Art. 75, II | D13: Placas de homenagem em aco inox (premio Honra ao Merito da Mulher Elza Carneiro) | E13: Flash Placas e Luminosos LTDA | F13: 2520 | G13: Concluido | H13: 32.99-0/03 | I13: Fabricacao de letras, letreiros e placas de qualquer material, exceto luminosos | J13: Sim | K13: 2026 | L13: REGISTRO_CONTRATACOES_2026.md #12; 24/03/2026
... A22: 21 | B22: PA 023/2026 - Dispensa 12/2026 | C22: Art. 75, II | D22: Recarga e manutencao de 2 extintores de incendio (CO2 6kg + AP 10L) | E22: Extinsul LTDA | F22: 493 | G22: Concluido (homologado) | H22: 33.14-7/10 | I22: Manutencao e reparacao de maquinas e equipamentos nao especificados anteriormente (inclui extintores) - alternativa: 82.99-7/99 | J22: Sim | K22: 2026 | L22: 08_processos_em_andamento/2026/24_DISPENSA_EXTINTORES; homologado ~29/06/2026
A24: Nota: os itens aquisicao de cadeiras, internet fibra redundante e micro-ondas da copa NAO constam desta tabela porque, conforme confirmado pelo usuario, ainda nao se tornaram processo licitatorio real (sem numero de processo, sem dispensa formalizada e, no caso de cadeiras, sem qualquer documento nos autos). Ver aba Itens em estudo (nao e processo).

Sheet Itens 013 e 016
A1: Processo | B1: Item n | C1: Descricao resumida | D1: Fornecedor | E1: Qtde | F1: V. Unit. (R$) | G1: V. Total (R$) | H1: CNAE (subclasse) | I1: Descricao CNAE
A2: 013/2026 | B2: 11 | C2: Tablet 10pol (10 unidades) | D2: ABR Acessorios LTDA | E2: 10 | F2: 1223.6 | G2: 12236 | H2: 47.51-2/01 | I2: Comercio varejista especializado de equipamentos e suprimentos de informatica
A3: 013/2026 | B3: 14 | C3: Caixa Acustica Ativa Tipo Coluna (2 unidades) | D3: ABR Acessorios LTDA | E3: 2 | F3: 1366.83 | G3: 2733.66 | H3: 47.53-9/00 | I3: Comercio varejista especializado de eletrodomesticos e equipamentos de audio e video
A4: 013/2026 | B4: 21 | C4: Switch de Rede 16 Portas Gigabit L2 | D4: ABR Acessorios LTDA | E4: 1 | F4: 762.86 | G4: 762.86 | H4: 47.51-2/01 | I4: Comercio varejista especializado de equipamentos e suprimentos de informatica
A5: 016/2026 | B5: 1 | C5: Suporte fixo de parede para TV (VESA) | D5: Antomig Solucoes Informatica LTDA | E5: 1 | F5: 30.5 | G5: 30.5 | H5: 47.53-9/00 | I5: Comercio varejista especializado de eletrodomesticos e equipamentos de audio e video
A6: 016/2026 | B6: 2 | C6: Combo teclado e mouse sem fio | D6: HM Informatica LTDA | E6: 1 | F6: 75 | G6: 75 | H6: 47.51-2/01 | I6: Comercio varejista especializado de equipamentos e suprimentos de informatica
A7: 016/2026 | B7: 3 | C7: Cabo de rede UTP CAT6 (305m) | D7: GWC Industria, Importacao e Distribuicao de Eletronicos LTDA | E7: 1 | F7: 899 | G7: 899 | H7: 47.51-2/01 | I7: Comercio varejista especializado de equipamentos e suprimentos de informatica
A8: 016/2026 | B8: 4 | C8: Conector RJ45 macho CAT6 blindado | D8: Antomig Solucoes Informatica LTDA | E8: 1 | F8: 100 | G8: 100 | H8: 47.51-2/01 | I8: Comercio varejista especializado de equipamentos e suprimentos de informatica
A9: 016/2026 | B9: 5 | C9: Painel de fechamento 1U p/ rack | D9: Incotech Company LTDA | E9: 5 | F9: 45 | G9: 225 | H9: 47.51-2/01 | I9: Comercio varejista especializado de equipamentos e suprimentos de informatica
A10: 016/2026 | B10: 6 | C10: Guia de cabos horizontal 1U p/ rack | D10: Rubens Dias da Cunha | E10: 3 | F10: 43 | G10: 129 | H10: 47.51-2/01 | I10: Comercio varejista especializado de equipamentos e suprimentos de informatica
A11: 016/2026 | B11: 7 | C11: Bandeja fixa 1U p/ rack | D11: ABR Acessorios LTDA | E11: 2 | F11: 59.85 | G11: 119.7 | H11: 47.51-2/01 | I11: Comercio varejista especializado de equipamentos e suprimentos de informatica
A12: 016/2026 | B12: 8 | C12: Kit de fixacao p/ rack (porca-gaiola e parafusos) | D12: ABR Acessorios LTDA | E12: 1 | F12: 89 | G12: 89 | H12: 47.51-2/01 | I12: Comercio varejista especializado de equipamentos e suprimentos de informatica
A13: 016/2026 | B13: 9 | C13: Regua de tomadas (PDU) p/ rack | D13: ABR Acessorios LTDA | E13: 1 | F13: 100.25 | G13: 100.25 | H13: 47.42-3/00 | I13: Comercio varejista de material eletrico
... A28: 016/2026 | B28: 25 | C28: Microfone de lapela sem fio | D28: Neocam Tecnologia Seguranca e Servicos LTDA | E28: 1 | F28: 485 | G28: 485 | H28: 47.53-9/00 | I28: Comercio varejista especializado de eletrodomesticos e equipamentos de audio e video
F29: Total: | G29: =SUM(G2:G28) -> 48806.47
A31: Item Nao Ofertado (V.Total = 0,00) de cada Homologacao foi excluido por nao representar despesa efetiva: item 1 (suporte de TV 60pol) do lote GL Tech no proc. 013/2026, e item 10 (kit eletrico) no proc. 016/2026. Console de mixagem e microfones profissionais foram classificados em 47.53-9/00 por analogia a equipamento de audio; ha entendimento alternativo que os enquadraria em comercio varejista de instrumentos musicais e acessorios (classe correlata) - recomenda-se confirmacao pontual no CONCLA se o valor acumulado desta subclasse se aproximar do limite.

Sheet Acumulado por CNAE
A1: CNAE (subclasse) | B1: Descricao | C1: Total acumulado 2026 (R$) | D1: Limite vigente inciso II (R$) | E1: Saldo ate o limite (R$) | F1: Alerta
A2: 77.11-0/00 | B2: Locacao de automoveis sem condutor | C2: =SUMIFS('Contratacoes 2026'!$F$2:$F$22,'Contratacoes 2026'!$H$2:$H$22,A2,'Contratacoes 2026'!$J$2:$J$22,"Sim")+SUMIFS('Itens 013 e 016'!$G$2:$G$28,'Itens 013 e 016'!$H$2:$H$28,A2) -> 18200 | D2: 65492.11 | E2: =D2-C2 -> 47292.11 | F2: =IF(C2>D2,"ULTRAPASSOU O LIMITE",IF(C2>0.8*D2,"ATENCAO: proximo do limite","OK")) -> OK
A3: 47.11-3/02 | B3: Comercio varejista de mercadorias em geral (supermercados) | C3: =SUMIFS('Contratacoes 2026'!$F$2:$F$22,'Contratacoes 2026'!$H$2:$H$22,A3,'Contratacoes 2026'!$J$2:$J$22,"Sim")+SUMIFS('Itens 013 e 016'!$G$2:$G$28,'Itens 013 e 016'!$H$2:$H$28,A3) -> 21892.75 | D3: 65492.11 | E3: =D3-C3 -> 43599.36 | F3: =IF(C3>D3,"ULTRAPASSOU O LIMITE",IF(C3>0.8*D3,"ATENCAO: proximo do limite","OK")) -> OK
A4: 47.61-0/03 | B4: Comercio varejista de artigos de papelaria | C4: =SUMIFS('Contratacoes 2026'!$F$2:$F$22,'Contratacoes 2026'!$H$2:$H$22,A4,'Contratacoes 2026'!$J$2:$J$22,"Sim")+SUMIFS('Itens 013 e 016'!$G$2:$G$28,'Itens 013 e 016'!$H$2:$H$28,A4) -> 14353.8 | D4: 65492.11 | E4: =D4-C4 -> 51138.31 | F4: =IF(C4>D4,"ULTRAPASSOU O LIMITE",IF(C4>0.8*D4,"ATENCAO: proximo do limite","OK")) -> OK
A5: 32.99-0/03 | B5: Fabricacao de letras, letreiros e placas | C5: =SUMIFS('Contratacoes 2026'!$F$2:$F$22,'Contratacoes 2026'!$H$2:$H$22,A5,'Contratacoes 2026'!$J$2:$J$22,"Sim")+SUMIFS('Itens 013 e 016'!$G$2:$G$28,'Itens 013 e 016'!$H$2:$H$28,A5) -> 2520 | D5: 65492.11 | E5: =D5-C5 -> 62972.11 | F5: =IF(C5>D5,"ULTRAPASSOU O LIMITE",IF(C5>0.8*D5,"ATENCAO: proximo do limite","OK")) -> OK
A6: 47.51-2/01 | B6: Comercio varejista de equip. e suprimentos de informatica | C6: =SUMIFS('Contratacoes 2026'!$F$2:$F$22,'Contratacoes 2026'!$H$2:$H$22,A6,'Contratacoes 2026'!$J$2:$J$22,"Sim")+SUMIFS('Itens 013 e 016'!$G$2:$G$28,'Itens 013 e 016'!$H$2:$H$28,A6) -> 26399.22 | D6: 65492.11 | E6: =D6-C6 -> 39092.89 | F6: =IF(C6>D6,"ULTRAPASSOU O LIMITE",IF(C6>0.8*D6,"ATENCAO: proximo do limite","OK")) -> OK
A7: 47.53-9/00 | B7: Comercio varejista de eletrodomesticos e equip. de audio/video | C7: =SUMIFS('Contratacoes 2026'!$F$2:$F$22,'Contratacoes 2026'!$H$2:$H$22,A7,'Contratacoes 2026'!$J$2:$J$22,"Sim")+SUMIFS('Itens 013 e 016'!$G$2:$G$28,'Itens 013 e 016'!$H$2:$H$28,A7) -> 17513.41 | D7: 65492.11 | E7: =D7-C7 -> 47978.7 | F7: =IF(C7>D7,"ULTRAPASSOU O LIMITE",IF(C7>0.8*D7,"ATENCAO: proximo do limite","OK")) -> OK
A8: 47.42-3/00 | B8: Comercio varejista de material eletrico | C8: =SUMIFS('Contratacoes 2026'!$F$2:$F$22,'Contratacoes 2026'!$H$2:$H$22,A8,'Contratacoes 2026'!$J$2:$J$22,"Sim")+SUMIFS('Itens 013 e 016'!$G$2:$G$28,'Itens 013 e 016'!$H$2:$H$28,A8) -> 385.25 | D8: 65492.11 | E8: =D8-C8 -> 65106.86 | F8: =IF(C8>D8,"ULTRAPASSOU O LIMITE",IF(C8>0.8*D8,"ATENCAO: proximo do limite","OK")) -> OK
A9: 47.52-1/00 | B9: Comercio varejista de equip. de telefonia e comunicacao | C9: =SUMIFS('Contratacoes 2026'!$F$2:$F$22,'Contratacoes 2026'!$H$2:$H$22,A9,'Contratacoes 2026'!$J$2:$J$22,"Sim")+SUMIFS('Itens 013 e 016'!$G$2:$G$28,'Itens 013 e 016'!$H$2:$H$28,A9) -> 9200 | D9: 65492.11 | E9: =D9-C9 -> 56292.11 | F9: =IF(C9>D9,"ULTRAPASSOU O LIMITE",IF(C9>0.8*D9,"ATENCAO: proximo do limite","OK")) -> OK
A10: 47.89-0/08 | B10: Comercio varejista de artigos fotograficos e para filmagem | C10: =SUMIFS('Contratacoes 2026'!$F$2:$F$22,'Contratacoes 2026'!$H$2:$H$22,A10,'Contratacoes 2026'!$J$2:$J$22,"Sim")+SUMIFS('Itens 013 e 016'!$G$2:$G$28,'Itens 013 e 016'!$H$2:$H$28,A10) -> 944.5 | D10: 65492.11 | E10: =D10-C10 -> 64547.61 | F10: =IF(C10>D10,"ULTRAPASSOU O LIMITE",IF(C10>0.8*D10,"ATENCAO: proximo do limite","OK")) -> OK
A11: 43.30-4/99 | B11: Outras obras de acabamento da construcao (claraboia - confirmar) | C11: =SUMIFS('Contratacoes 2026'!$F$2:$F$22,'Contratacoes 2026'!$H$2:$H$22,A11,'Contratacoes 2026'!$J$2:$J$22,"Sim")+SUMIFS('Itens 013 e 016'!$G$2:$G$28,'Itens 013 e 016'!$H$2:$H$28,A11) -> 2780 | D11: 65492.11 | E11: =D11-C11 -> 62712.11 | F11: =IF(C11>D11,"ULTRAPASSOU O LIMITE",IF(C11>0.8*D11,"ATENCAO: proximo do limite","OK")) -> OK
A12: 33.14-7/10 | B12: Manutencao e reparacao de maquinas/equipamentos (extintores) | C12: =SUMIFS('Contratacoes 2026'!$F$2:$F$22,'Contratacoes 2026'!$H$2:$H$22,A12,'Contratacoes 2026'!$J$2:$J$22,"Sim")+SUMIFS('Itens 013 e 016'!$G$2:$G$28,'Itens 013 e 016'!$H$2:$H$28,A12) -> 493 | D12: 65492.11 | E12: =D12-C12 -> 64999.11 | F12: =IF(C12>D12,"ULTRAPASSOU O LIMITE",IF(C12>0.8*D12,"ATENCAO: proximo do limite","OK")) -> OK
A13: 63.19-4/00 | B13: Portais/servicos de informacao (certificacao digital) - SEM ratificacao | C13: =SUMIFS('Contratacoes 2026'!$F$2:$F$22,'Contratacoes 2026'!$H$2:$H$22,A13,'Contratacoes 2026'!$J$2:$J$22,"Sim")+SUMIFS('Itens 013 e 016'!$G$2:$G$28,'Itens 013 e 016'!$H$2:$H$28,A13) -> 0 | D13: 65492.11 | E13: =D13-C13 -> 65492.11 | F13: =IF(C13>D13,"ULTRAPASSOU O LIMITE",IF(C13>0.8*D13,"ATENCAO: proximo do limite","OK")) -> OK
A15: Nota: limite de R$ 65.492,11 (inciso II) citado nos autos com base no Decreto no 12.807/2025, exercicio 2026. O arquivo 01_legislacao/limites-vigentes-dispensa-art-75.md ainda esta com o valor oficial marcado como [CONFIRMAR] - validar antes de qualquer decisao formal. A linha 63.19-4/00 (certificado digital) aparece zerada de proposito: o processo (R$158,00, Imperio Certificados) ainda nao foi ratificado/homologado, entao nao entra no acumulado ate ser formalizado - adicione manualmente se e quando o processo for concluido. Inexigibilidades (art. 74) tambem nao entram nesta soma por nao se sujeitarem ao limite do art. 75, I/II.

Sheet Itens em estudo
A1: Item | B1: Situacao | C1: Documentos existentes | D1: CNAE provavel (se/quando virar processo)
A2: Aquisicao de cadeiras | B2: NAO e processo real ainda - sem numero de processo, sem DFD/TR/dispensa nos autos | C2: Nenhum documento formal (apenas mencao no indice de precedentes) | D2: 47.54-7/01 - Comercio varejista de moveis
A3: Internet fibra optica redundante (link secundario) | B3: NAO e processo real ainda - apenas DFD e Termo de Referencia elaborados; sem dispensa aberta, sem pesquisa de precos concluida | C3: DFD_Internet_Fibra_Redundante_Camara_Itanhandu.docx/.pdf; TR_Internet_Fibra_Redundante_Camara_Itanhandu_final.docx | D3: 61.10-8/03 - Servico de comunicacao multimidia (SCM)
A4: Micro-ondas para a copa | B4: NAO e processo real ainda - apenas DFD em elaboracao, com campos [PREENCHER] em aberto | C4: DFD_Microondas_Copa_2026.docx | D4: 47.53-9/00 - Comercio varejista especializado de eletrodomesticos e equipamentos de audio e video
